logg3r.py
logg3r-2.0.2.dist-info/LICENSE
logg3r-2.0.2.dist-info/METADATA
logg3r-2.0.2.dist-info/WHEEL
logg3r-2.0.2.dist-info/top_level.txt
logg3r-2.0.2.dist-info/RECORD
