Metadata-Version: 2.1
Name: logg3r
Version: 2.0.2
Summary: Simple python log helper
Home-page: https://github.com/mghelton/logg3r
Author: Gage Helton
Author-email: gagehelton@gmail.com
License: UNKNOWN
Platform: UNKNOWN
Classifier: Programming Language :: Python :: 3
Classifier: License :: OSI Approved :: MIT License
Classifier: Operating System :: OS Independent
